{
  "architecture": {
    "name": "Architecture",
    "links": [
      {
        "name": "Residential",
        "isExpandable": true,
        "link": "/architecture/residential"
      },
      {
        "name": "Commercial",
        "isExpandable": false,
        "link": "/architecture/commercial"
      },
      {
        "name": "Planning Applications",
        "isExpandable": false,
        "link": "/architecture/planning-applications"
      },
      {
        "name": "Building Control DWG",
        "isExpandable": false,
        "link": "/architecture/building-control-dwg"
      },
      {
        "name": "Change of Use",
        "isExpandable": false,
        "link": "/architecture/change-of-use"
      },
      {
        "name": "New Build",
        "isExpandable": false,
        "link": "/architecture/new-build"
      },
      {
        "name": "Structural Engineering",
        "isExpandable": false,
        "link": "/architecture/structural-engineering"
      }
    ]
  },
  "interiors": {
    "name": "Interiors",
    "links": [
      {
        "name": "How It Works",
        "isExpandable": false,
        "link": "/interiors/how-it-works"
      },
      {
        "name": "Residential",
        "isExpandable": true,
        "link": "/interiors/residential"
      },
      {
        "name": "Commercial",
        "isExpandable": false,
        "link": "/interiors/commercial"
      }
    ]
  },
  "construction": {
    "name": "Construction",
    "links": [
      {
        "name": "About",
        "isExpandable": false,
        "link": "/construction/about"
      },
      {
        "name": "Domestic",
        "isExpandable": false,
        "link": "/construction/domestic"
      },
      {
        "name": "Commercial",
        "isExpandable": false,
        "link": "/construction/commercial"
      },
      {
        "name": "Industrial",
        "isExpandable": false,
        "link": "/construction/industrial"
      },
      {
        "name": "Project Management",
        "isExpandable": false,
        "link": "/construction/project-management"
      }
    ]
  }
}
